glimy/__init__.py
glimy/geo.py
glimy-5.0.1.dist-info/LICENSE
glimy-5.0.1.dist-info/METADATA
glimy-5.0.1.dist-info/WHEEL
glimy-5.0.1.dist-info/top_level.txt
glimy-5.0.1.dist-info/RECORD
