Metadata-Version: 2.1
Name: glimy
Version: 5.0.1
Summary: Computational Electromagnetics Package with Dielectic, Magnetic, Anisotropic, Lossy Materials and Gravity
Author-email: Ali Hakim Taskiran <alihakimxyz@gmail.com>
License: GNU GENERAL PUBLIC LICENSE
Project-URL: Homepage, https://github.com/alihakimtaskiran/Glimy
Project-URL: Bug Tracker, https://github.com/alihakimtaskiran/Glimy/issues
Classifier: Programming Language :: Python :: 3
Classifier: License :: OSI Approved :: GNU General Public License v3 (GPLv3)
Classifier: Operating System :: OS Independent
Requires-Python: >=3.6
License-File: LICENSE
Requires-Dist: numpy
Requires-Dist: matplotlib
Requires-Dist: psutil
